setup.py
setup_client.py
client/__init__.py
client/client.py
client/setup.py
client/client/__init__.py
client/client/add_contact.py
client/client/database.py
client/client/del_contact.py
client/client/main_window.py
client/client/main_window_conv.py
client/client/start_dialog.py
client/client/transport.py
client/common/__init__.py
client/common/decos.py
client/common/descryptors.py
client/common/errors.py
client/common/metaclasses.py
client/common/utils.py
client/common/variables.py
client/logs/__init__.py
client/logs/config_client_log.py
client/logs/config_server_log.py
mess_client_serzh.egg-info/PKG-INFO
mess_client_serzh.egg-info/SOURCES.txt
mess_client_serzh.egg-info/dependency_links.txt
mess_client_serzh.egg-info/requires.txt
mess_client_serzh.egg-info/top_level.txt