Metadata-Version: 1.0
Name: mess-client-serzh
Version: 0.0.3
Summary: mess_client_proj
Home-page: UNKNOWN
Author: Ivan Ivanov
Author-email: iv.iv@yandex.ru
License: UNKNOWN
Platform: UNKNOWN
